djangocms_page_meta/__init__.py
djangocms_page_meta/admin.py
djangocms_page_meta/apps.py
djangocms_page_meta/cms_toolbars.py
djangocms_page_meta/forms.py
djangocms_page_meta/models.py
djangocms_page_meta/settings.py
djangocms_page_meta/utils.py
djangocms_page_meta/locale/ar/LC_MESSAGES/django.mo
djangocms_page_meta/locale/ar/LC_MESSAGES/django.po
djangocms_page_meta/locale/bg/LC_MESSAGES/django.mo
djangocms_page_meta/locale/bg/LC_MESSAGES/django.po
djangocms_page_meta/locale/de/LC_MESSAGES/django.mo
djangocms_page_meta/locale/de/LC_MESSAGES/django.po
djangocms_page_meta/locale/en/LC_MESSAGES/django.mo
djangocms_page_meta/locale/en/LC_MESSAGES/django.po
djangocms_page_meta/locale/es/LC_MESSAGES/django.mo
djangocms_page_meta/locale/es/LC_MESSAGES/django.po
djangocms_page_meta/locale/it/LC_MESSAGES/django.mo
djangocms_page_meta/locale/it/LC_MESSAGES/django.po
djangocms_page_meta/locale/lt/LC_MESSAGES/django.mo
djangocms_page_meta/locale/lt/LC_MESSAGES/django.po
djangocms_page_meta/locale/pt_BR/LC_MESSAGES/django.mo
djangocms_page_meta/locale/pt_BR/LC_MESSAGES/django.po
djangocms_page_meta/locale/ru/LC_MESSAGES/django.mo
djangocms_page_meta/locale/ru/LC_MESSAGES/django.po
djangocms_page_meta/locale/tr/LC_MESSAGES/django.mo
djangocms_page_meta/locale/tr/LC_MESSAGES/django.po
djangocms_page_meta/migrations/0001_initial.py
djangocms_page_meta/migrations/0002_auto_20150807_0936.py
djangocms_page_meta/migrations/0003_auto_20151220_1734.py
djangocms_page_meta/migrations/0004_auto_20160409_1852.py
djangocms_page_meta/migrations/0005_pagemeta_fb_pages.py
djangocms_page_meta/migrations/0006_auto_20160423_1859.py
djangocms_page_meta/migrations/0007_auto_20160530_2257.py
djangocms_page_meta/migrations/0008_auto_20160609_0754.py
djangocms_page_meta/migrations/0009_auto_20171230_1954.py
djangocms_page_meta/migrations/0010_auto_20180108_2316.py
djangocms_page_meta/migrations/0011_auto_20190218_1010.py
djangocms_page_meta/migrations/0012_auto_20200706_1230.py
djangocms_page_meta-1.4.5.dist-info/LICENSE
djangocms_page_meta-1.4.5.dist-info/METADATA
djangocms_page_meta-1.4.5.dist-info/WHEEL
djangocms_page_meta-1.4.5.dist-info/top_level.txt
djangocms_page_meta-1.4.5.dist-info/RECORD
